alert_on_exception/__init__.py
alert_on_exception/alert.py
alert_on_exception-0.1.7.dist-info/LICENSE
alert_on_exception-0.1.7.dist-info/METADATA
alert_on_exception-0.1.7.dist-info/WHEEL
alert_on_exception-0.1.7.dist-info/top_level.txt
alert_on_exception-0.1.7.dist-info/RECORD
