Metadata-Version: 2.1
Name: alert_on_exception
Version: 0.1.7
Summary: A Python package to alert users about exceptions.
Requires-Python: >=3.6
License-File: LICENSE
